redis_dict/__init__.py
redis_dict/core.py
redis_dict/py.typed
redis_dict/python_dict.py
redis_dict/type_management.py
redis_dict-3.2.5.dist-info/licenses/LICENSE
redis_dict-3.2.5.dist-info/METADATA
redis_dict-3.2.5.dist-info/WHEEL
redis_dict-3.2.5.dist-info/top_level.txt
redis_dict-3.2.5.dist-info/RECORD
