Metadata-Version: 2.4
Name: redis-dict
Version: 3.2.5
Summary: Dictionary with Redis as storage backend
Author-email: Melvin Bijman <bijman.m.m@gmail.com>
License: MIT
Project-URL: Homepage, https://github.com/Attumm/redisdict
Project-URL: Documentation, https://attumm.github.io/redis-dict/
Project-URL: Repository, https://github.com/Attumm/redisdict.git
Project-URL: Changelog, https://github.com/Attumm/redisdict/releases
Keywords: redis,python,dictionary,dict,key-value,database,caching,distributed-computing,dictionary-interface,large-datasets,scientific-computing,data-persistence,high-performance,scalable,pipelining,batching,big-data,data-types,distributed-algorithms,encryption,data-management
Classifier: Development Status :: 5 - Production/Stable
Classifier: Intended Audience :: Developers
Classifier: Intended Audience :: Information Technology
Classifier: Intended Audience :: Science/Research
Classifier: Topic :: Internet
Classifier: Topic :: Scientific/Engineering
Classifier: Topic :: Database
Classifier: Topic :: System :: Distributed Computing
Classifier: Topic :: Software Development :: Libraries :: Python Modules
Classifier: Topic :: Software Development :: Object Brokering
Classifier: Topic :: Database :: Database Engines/Servers
Classifier: License :: OSI Approved :: MIT License
Classifier: Programming Language :: Python :: 3
Classifier: Programming Language :: Python :: 3.8
Classifier: Programming Language :: Python :: 3.9
Classifier: Programming Language :: Python :: 3.10
Classifier: Programming Language :: Python :: 3.11
Classifier: Programming Language :: Python :: 3.12
Classifier: Typing :: Typed
Requires-Python: >=3.8
License-File: LICENSE
Requires-Dist: redis>=4.0.0
Provides-Extra: dev
Requires-Dist: coverage==5.5; extra == "dev"
Requires-Dist: hypothesis==6.70.1; extra == "dev"
Requires-Dist: mypy>=1.8.0; extra == "dev"
Requires-Dist: mypy-extensions>=1.0.0; extra == "dev"
Requires-Dist: types-pyOpenSSL>=24.0.0.0; extra == "dev"
Requires-Dist: types-redis>=4.6.0; extra == "dev"
Requires-Dist: typing_extensions>=4.5.0; extra == "dev"
Requires-Dist: attrs==22.2.0; extra == "dev"
Requires-Dist: cffi==1.15.1; extra == "dev"
Requires-Dist: cryptography==44.0.1; extra == "dev"
Requires-Dist: exceptiongroup==1.1.1; extra == "dev"
Requires-Dist: future==0.18.3; extra == "dev"
Requires-Dist: pycparser==2.21; extra == "dev"
Requires-Dist: snowballstemmer==2.2.0; extra == "dev"
Requires-Dist: sortedcontainers==2.4.0; extra == "dev"
Requires-Dist: tomli==2.0.1; extra == "dev"
Requires-Dist: setuptools>=68.0.0; extra == "dev"
Requires-Dist: bandit; extra == "dev"
Requires-Dist: pylama>=8.4.1; extra == "dev"
Requires-Dist: pycodestyle==2.10.0; extra == "dev"
Requires-Dist: pydocstyle==6.3.0; extra == "dev"
Requires-Dist: pyflakes==3.0.1; extra == "dev"
Requires-Dist: mccabe==0.7.0; extra == "dev"
Requires-Dist: pylint==3.2.7; extra == "dev"
Requires-Dist: darglint; extra == "dev"
Requires-Dist: pydocstyle; extra == "dev"
Requires-Dist: autopep8; extra == "dev"
Provides-Extra: docs
Requires-Dist: sphinx; extra == "docs"
Requires-Dist: sphinx-rtd-theme; extra == "docs"
Requires-Dist: sphinx-autodoc-typehints; extra == "docs"
Requires-Dist: tomli; extra == "docs"
Requires-Dist: myst-parser; extra == "docs"
Provides-Extra: build
Requires-Dist: build; extra == "build"
Requires-Dist: twine; extra == "build"
Dynamic: license-file
